setup.cfg
setup.py
host_profiler/__init__.py
host_profiler/bench.py
host_profiler/benchproc.py
host_profiler.egg-info/PKG-INFO
host_profiler.egg-info/SOURCES.txt
host_profiler.egg-info/dependency_links.txt
host_profiler.egg-info/requires.txt
host_profiler.egg-info/top_level.txt
scripts/runbench