Metadata-Version: 1.0
Name: host-profiler
Version: 0.7
Summary: get host informations
Home-page: http://github.com/dowan/host_profiler
Author: Dowan
Author-email: contact@dowan.beer
License: MIT
Keywords: profiler,bench,psutil
Platform: UNKNOWN
